MANIFEST.in
README.txt
setup.cfg
setup.py
django_swstags.egg-info/PKG-INFO
django_swstags.egg-info/SOURCES.txt
django_swstags.egg-info/dependency_links.txt
django_swstags.egg-info/top_level.txt
sws_tags/__init__.py
sws_tags/models.py
sws_tags/tests.py
sws_tags/views.py
sws_tags/static/css/base_tag_template.css
sws_tags/static/js/control_code.js
sws_tags/static/js/utils.js
sws_tags/sws_utils/__init__.py
sws_tags/sws_utils/circus_utils.py
sws_tags/sws_utils/common_utils.py
sws_tags/sws_utils/contaplus.py
sws_tags/sws_utils/cube.py
sws_tags/sws_utils/cube_utils.py
sws_tags/sws_utils/date.py
sws_tags/sws_utils/decorators.py
sws_tags/sws_utils/decorators_lua.py
sws_tags/sws_utils/excel.py
sws_tags/sws_utils/filters.py
sws_tags/sws_utils/highcharts.py
sws_tags/sws_utils/mail.py
sws_tags/sws_utils/messages.py
sws_tags/sws_utils/pdf_utils.py
sws_tags/sws_utils/profile.py
sws_tags/sws_utils/xlsx.py
sws_tags/templates/tags/pdf_format.html
sws_tags/templates/tags/pdf_format_old.html
sws_tags/templates/tags/tag_button.html
sws_tags/templates/tags/tag_csvupload.html
sws_tags/templates/tags/tag_drag_and_drop.html
sws_tags/templates/tags/tag_drag_and_drop2.html
sws_tags/templates/tags/tag_excel_csv.html
sws_tags/templates/tags/tag_filters.html
sws_tags/templates/tags/tag_filters_date.html
sws_tags/templates/tags/tag_filters_select2.html
sws_tags/templates/tags/tag_filters_text.html
sws_tags/templates/tags/tag_footer.html
sws_tags/templates/tags/tag_grid.html
sws_tags/templates/tags/tag_grid_dict.html
sws_tags/templates/tags/tag_group_by.html
sws_tags/templates/tags/tag_highcharts.html
sws_tags/templates/tags/tag_highstock.html
sws_tags/templates/tags/tag_highstock2.html
sws_tags/templates/tags/tag_individual_filters.html
sws_tags/templates/tags/tag_interruptor.html
sws_tags/templates/tags/tag_legend.html
sws_tags/templates/tags/tag_mail.html
sws_tags/templates/tags/tag_moreless.html
sws_tags/templates/tags/tag_refresh_time.html
sws_tags/templates/tags/tag_shortcuts.html
sws_tags/templates/tags/tag_slider.html
sws_tags/templates/tags/tag_speedometer.html
sws_tags/templates/tags/tag_table.html
