Metadata-Version: 1.0
Name: django-swstags
Version: 0.10.4
Summary: UNKNOWN
Home-page: http://www.stoneworksolutions.net
Author: Miguel Angel Sanchez
Author-email: miguel.sanchez@stoneworksolutions.net
License: UNKNOWN
Platform: UNKNOWN
